codestack/.env.example
codestack/__init__.py
codestack/app.py
codestack/preview.py
codestack/prompt.py
codestack/spinner.py
codestack-0.1.3.dist-info/licenses/LICENSE
codestack-0.1.3.dist-info/METADATA
codestack-0.1.3.dist-info/WHEEL
codestack-0.1.3.dist-info/top_level.txt
codestack-0.1.3.dist-info/RECORD
