Metadata-Version: 2.4
Name: codestack
Version: 0.1.3
Summary: AI-powered developer that transforms natural language instructions into complete, runnable projects for any tech stack.
Home-page: https://github.com/AdityaTheDev/codestack
Author: Aditya Hariharan
Author-email: aditya.h@zohomail.in
License: MIT
Classifier: License :: OSI Approved :: MIT License
Requires-Python: >=3.9
License-File: LICENSE
Requires-Dist: python-dotenv==1.1.1
Requires-Dist: google-generativeai==0.8.5
Dynamic: author
Dynamic: author-email
Dynamic: classifier
Dynamic: description
Dynamic: description-content-type
Dynamic: home-page
Dynamic: license
Dynamic: license-file
Dynamic: requires-dist
Dynamic: requires-python
Dynamic: summary
